experiment_config/__init__.py
experiment_config/command.py
experiment_config/config.py
experiment_config_jvasilakes-0.0.1.dist-info/LICENSE
experiment_config_jvasilakes-0.0.1.dist-info/METADATA
experiment_config_jvasilakes-0.0.1.dist-info/WHEEL
experiment_config_jvasilakes-0.0.1.dist-info/top_level.txt
experiment_config_jvasilakes-0.0.1.dist-info/RECORD
