Metadata-Version: 2.1
Name: experiment_config_jvasilakes
Version: 0.0.1
Summary: A package for configuring and logging ML experiments
Author-email: Jake Vasilakes <jvasialkes@gmail.com>
Project-URL: Homepage, https://github.com/jvasilakes/experiment-config
Classifier: Programming Language :: Python :: 3
Classifier: License :: OSI Approved :: MIT License
Classifier: Operating System :: OS Independent
Requires-Python: >=3.8
License-File: LICENSE
